create_pypi_skeleton/__init__.py
create_pypi_skeleton/__main__.py
create_pypi_skeleton-0.0.11.dist-info/METADATA
create_pypi_skeleton-0.0.11.dist-info/WHEEL
create_pypi_skeleton-0.0.11.dist-info/licenses/LICENSE
create_pypi_skeleton-0.0.11.dist-info/RECORD
