Metadata-Version: 2.4
Name: create_pypi_skeleton
Version: 0.0.11
Summary: This module automatically creates a PyPI project skeleton for you so you don't have to do this manually.
Project-URL: Homepage, https://github.com/zlliu246/create_pypi_skeleton
Project-URL: Issues, https://github.com/zlliu246/create_pypi_skeleton/issues
Author-email: Liu Zuo Lin <zlliu246@gmail.com>
License-File: LICENSE
Classifier: License :: OSI Approved :: MIT License
Classifier: Operating System :: OS Independent
Classifier: Programming Language :: Python :: 3
Requires-Python: >=3.8
